[
    {
        "id": "hgafr44",
        "date": "23-2-2019",
        "updated": "25-2-2019 (09:07)",
        "title": "eyeore sad",
        "email": "crobin@poobear.com",
        "details": "silly boy",
        "status": "2",
        "impact": "fish pie"
    },
    {
        "id": "1672",
        "date": "22-2-2019",
        "updated": "22-2-2019 (13:09)",
        "title": "jolly google",
        "email": "xsdes@gmail.com",
        "details": "slarty bartfast",
        "status": "1",
        "impact": "no much really"
    }
]