[
    {
        "id": "inc00000012",
        "date": "12-01-19 (13:10)",
        "updated": "01-02-19 (13:10)",
        "title": "broken links",
        "email": "devierte@hhh.com",
        "details": "problem with  . . . .",
        "status": 1,
        "impact": "Whatever, yada yada yada . . ."
    },
    {
        "id": "inc000012345678",
        "date": "22-2-2019 (13:10)",
        "updated": "22-2-2019 (13:20)",
        "title": "test p1 ticket create",
        "email": "kappiweb@gmail.com",
        "details": "problem with  . . . .",
        "status": "1",
        "impact": "gfhgfhfhhhhh"
    }
]